Workbook
Name aporte: APP!$D$15
Name perfil_valor: APP!$C$29
Name qtd_anos: APP!$D$16
Name rendimento_carteira: APP!$D$11
Name salario: APP!$D$10
Name taxa_mensal: APP!$D$17

Sheet APP
B9: CONFIGURAÇÕES
B10: Salário | D10: 5000
B11: Rendimento Carteira | D11: 0.006
B12: Sugestão de Investimento | D12: =salario*30% -> 1500
B14: INVESTIMENTO MENSAL
B15: Quanto investir por mês? | D15: 500
B16: Por quantos Anos? | D16: 5
B17: Taxa de Rendimento mensal? | D17: 0.01079
B18: Patrimônio acumulado? | D18: =FV(taxa_mensal,qtd_anos*12,aporte*-1) -> 41888.457
B19: Dividendos Mensais? | D19: =D18*$D$11 -> 251.33074
B21: CENÁRIOS | D21: DIVIDENDOS
B22: Quanto em 2 Anos? | C22: =FV($D$17,2*12,$D$15*-1) -> 13613.814 | D22: =C22*rendimento_carteira -> 81.682882
B23: Quanto em 5 Anos? | C23: =FV($D$17,5*12,$D$15*-1) -> 41888.457 | D23: =C23*rendimento_carteira -> 251.33074
B24: Quanto em 10 Anos? | C24: =FV($D$17,10*12,$D$15*-1) -> 121642.11 | D24: =C24*rendimento_carteira -> 729.85264
B25: Quanto em 20 Anos? | C25: =FV($D$17,20*12,$D$15*-1) -> 562599.2 | D25: =C25*rendimento_carteira -> 3375.5952
B26: Quanto em 30 Anos? | C26: =FV($D$17,30*12,$D$15*-1) -> 2161084.8 | D26: =C26*rendimento_carteira -> 12966.509
B28: PERFIL | C28: Agressivo
B29: VALOR A SER INVESTIDO POR MÊS | C29: =aporte -> 500
B31: TIPO DE FII | C31: Percentual Sugerido | D31: Valores
B32: PAPEL | C32: =VLOOKUP($C$28&"-"&B32,Plan2!$B:$E,4,) -> 0.5 | D32: =perfil_valor*C32 -> 250
B33: TIJOLO | C33: =VLOOKUP($C$28&"-"&B33,Plan2!$B:$E,4,) -> 0.1 | D33: =perfil_valor*C33 -> 50
B34: HÍBRIDOS | C34: =VLOOKUP($C$28&"-"&B34,Plan2!$B:$E,4,) -> 0.05 | D34: =perfil_valor*C34 -> 25
B35: FOFs | C35: =VLOOKUP($C$28&"-"&B35,Plan2!$B:$E,4,) -> 0.05 | D35: =perfil_valor*C35 -> 25
B36: DESENVOLVIMENTO | C36: =VLOOKUP($C$28&"-"&B36,Plan2!$B:$E,4,) -> 0.2 | D36: =perfil_valor*C36 -> 100
B37: HOTELARIAS | C37: =VLOOKUP($C$28&"-"&B37,Plan2!$B:$E,4,) -> 0.1 | D37: =perfil_valor*C37 -> 50
D38: =SUM(D32:D37) -> 500

Sheet Plan2
B2: CHAVE | C2: PERFIL | D2: TIPO DE FII | E2: %
B3: =C3&"-"&D3 -> Conservador-PAPEL | C3: Conservador | D3: PAPEL | E3: 0.3
B4: =C4&"-"&D4 -> Conservador-TIJOLO | C4: Conservador | D4: TIJOLO | E4: 0.5
B5: =C5&"-"&D5 -> Conservador-HÍBRIDOS | C5: Conservador | D5: HÍBRIDOS | E5: 0.1
B6: =C6&"-"&D6 -> Conservador-FOFs | C6: Conservador | D6: FOFs | E6: 0.1
B7: =C7&"-"&D7 -> Conservador-DESENVOLVIMENTO | C7: Conservador | D7: DESENVOLVIMENTO | E7: 0
B8: =C8&"-"&D8 -> Conservador-HOTELARIAS | C8: Conservador | D8: HOTELARIAS | E8: 0
B9: =C9&"-"&D9 -> Moderado-PAPEL | C9: Moderado | D9: PAPEL | E9: 0.32
B10: =C10&"-"&D10 -> Moderado-TIJOLO | C10: Moderado | D10: TIJOLO | E10: 0.35
B11: =C11&"-"&D11 -> Moderado-HÍBRIDOS | C11: Moderado | D11: HÍBRIDOS | E11: 0.08
B12: =C12&"-"&D12 -> Moderado-FOFs | C12: Moderado | D12: FOFs | E12: 0.05
B13: =C13&"-"&D13 -> Moderado-DESENVOLVIMENTO | C13: Moderado | D13: DESENVOLVIMENTO | E13: 0.1
B14: =C14&"-"&D14 -> Moderado-HOTELARIAS | C14: Moderado | D14: HOTELARIAS | E14: 0.1
... B20: =C20&"-"&D20 -> Agressivo-HOTELARIAS | C20: Agressivo | D20: HOTELARIAS | E20: 0.1
